{
    "survey": [
        {
            "accountId": "001M000000RnyS3IAJ",
            "question": "When is training scheduled",
            "questionType": null,
            "questionTypeId": null,
            "answers": "Yes;N/A"
        },
        {
            "accountId": "001M000000RnyS3IAJ",
            "question": "rsad",
            "questionType": null,
            "questionTypeId": null,
            "answers": "Yes"
        },
        {
            "accountId": "001M000000RnyS3IAJ",
            "question": "market survey",
            "questionType": null,
            "questionTypeId": null,
            "answers": "Yes;No"
        },
        {
            "accountId": "001M000000RnyS3IAJ",
            "question": "QuestionTuesday",
            "questionType": null,
            "questionTypeId": null,
            "answers": "Yes;No;N/A"
        },
        {
            "accountId": "001M000000RnyS3IAJ",
            "question": "question 2 tue",
            "questionType": null,
            "questionTypeId": null,
            "answers": "Yes;No"
        },
        {
            "accountId": "001M000000RnyS3IAJ",
            "question": "How many Diplay units are there ?",
            "questionType": null,
            "questionTypeId": null,
            "answers": "Yes;No;N/A"
        },
        {
            "accountId": "001M000000RnyS3IAJ",
            "question": null,
            "questionType": null,
            "questionTypeId": null,
            "answers": null
        },
        {
            "accountId": "001M000000RnyS3IAJ",
            "question": null,
            "questionType": null,
            "questionTypeId": null,
            "answers": null
        },
        {
            "accountId": "001M000000RnyS3IAJ",
            "question": null,
            "questionType": null,
            "questionTypeId": null,
            "answers": null
        },
        {
            "accountId": "001M000000RnyS3IAJ",
            "question": null,
            "questionType": null,
            "questionTypeId": null,
            "answers": null
        },
        {
            "accountId": "001M000000RnyS3IAJ",
            "question": null,
            "questionType": null,
            "questionTypeId": null,
            "answers": null
        },
        {
            "accountId": "001M000000RnyS3IAJ",
            "question": "Have you completed your time sheets",
            "questionType": null,
            "questionTypeId": null,
            "answers": null
        },
        {
            "accountId": "001M000000RnyS3IAJ",
            "question": "Schedule Roadnet?",
            "questionType": null,
            "questionTypeId": null,
            "answers": "Yes;No"
        },
        {
            "accountId": "001M000000RnyS3IAJ",
            "question": "different question",
            "questionType": null,
            "questionTypeId": null,
            "answers": null
        },
        {
            "accountId": "001M000000SMnFaIAL",
            "question": "rsad",
            "questionType": null,
            "questionTypeId": null,
            "answers": "Yes"
        },
        {
            "accountId": "001M000000SMnFaIAL",
            "question": "QuestionTuesday",
            "questionType": null,
            "questionTypeId": null,
            "answers": "Yes;No;N/A"
        },
        {
            "accountId": "001M000000SMnFaIAL",
            "question": "How many Diplay units are there ?",
            "questionType": null,
            "questionTypeId": null,
            "answers": "Yes;No;N/A"
        },
        {
            "accountId": "001M000000SMnFaIAL",
            "question": "ddddttttt",
            "questionType": null,
            "questionTypeId": null,
            "answers": null
        },
        {
            "accountId": "001M000000SMnFaIAL",
            "question": "different question",
            "questionType": null,
            "questionTypeId": null,
            "answers": null
        },
        {
            "accountId": "001M000000SMnFaIAL",
            "question": "t",
            "questionType": null,
            "questionTypeId": null,
            "answers": null
        },
        {
            "accountId": "001M000000Sv5L6IAJ",
            "question": "QuestionTuesday",
            "questionType": null,
            "questionTypeId": null,
            "answers": "Yes;No;N/A"
        },
        {
            "accountId": "001M000000Sv5L6IAJ",
            "question": "How many Diplay units are there ?",
            "questionType": null,
            "questionTypeId": null,
            "answers": "Yes;No;N/A"
        }
    ],
    "priorities": [
        {
            "accountId": "001M000000RnyS3IAJ",
            "title": null,
            "description": "need dates"
        }
    ],
    "promotions": [
        {
            "startDate": null,
            "promotionItem": [
                {
                    "productDescription": "SPDRK 3PK 123G 12",
                    "promotionItemListPrice": "100.0",
                    "salesPrice": "100.0",
                    "productNumber": "1024500105013"
                }
            ],
            "accountId": null,
            "orderItemDiscount": "true",
            "discountAmount": null,
            "discountPercentage": "0.2",
            "endDate": null,
            "title": "Promotion 1",
            "description": null
        },
        {
            "startDate": "2013-10-03",
            "promotionItem": [],
            "accountId": null,
            "orderItemDiscount": "false",
            "discountAmount": null,
            "discountPercentage": "0.0",
            "endDate": "2013-10-31",
            "title": "Exhibitor KitKat",
            "description": "Exhibitor KitKat"
        },
        {
            "startDate": "2013-10-04",
            "promotionItem": [
                {
                    "productDescription": "Exhibitor Hershey Bar",
                    "promotionItemListPrice": "0.0",
                    "salesPrice": "0.0",
                    "productNumber": null
                }
            ],
            "accountId": null,
            "orderItemDiscount": "false",
            "discountAmount": null,
            "discountPercentage": "0.0",
            "endDate": "2013-12-31",
            "title": "Exhibitor Hershey Bar",
            "description": null
        },
        {
            "startDate": "2013-10-04",
            "promotionItem": [],
            "accountId": null,
            "orderItemDiscount": "true",
            "discountAmount": null,
            "discountPercentage": "0.1",
            "endDate": "2013-12-31",
            "title": "Total Order Discount 10%",
            "description": "Total Order Discount 10%"
        },
        {
            "startDate": "2013-10-03",
            "promotionItem": [
                {
                    "productDescription": null,
                    "promotionItemListPrice": "0.0",
                    "salesPrice": "0.0",
                    "productNumber": "11111111111"
                }
            ],
            "accountId": null,
            "orderItemDiscount": "false",
            "discountAmount": null,
            "discountPercentage": "0.0",
            "endDate": "2013-10-31",
            "title": "Exhibitor KitKat",
            "description": "Exhibitor KitKat"
        },
        {
            "startDate": "2013-10-04",
            "promotionItem": [],
            "accountId": null,
            "orderItemDiscount": "true",
            "discountAmount": "-1.0",
            "discountPercentage": "0.0",
            "endDate": "2013-12-31",
            "title": "Open Promotion",
            "description": "Open Promotion"
        },
        {
            "startDate": "2013-10-04",
            "promotionItem": [],
            "accountId": null,
            "orderItemDiscount": "false",
            "discountAmount": null,
            "discountPercentage": "0.0",
            "endDate": "2013-12-31",
            "title": "Buy 10 Eaches of KitKat get Calculator free",
            "description": "Buy 10 Eaches of KitKat get Calculator free"
        },
        {
            "startDate": "2013-10-09",
            "promotionItem": [
                {
                    "productDescription": null,
                    "promotionItemListPrice": "2.0",
                    "salesPrice": "1.0",
                    "productNumber": null
                }
            ],
            "accountId": null,
            "orderItemDiscount": "false",
            "discountAmount": null,
            "discountPercentage": "0.0",
            "endDate": "2013-10-23",
            "title": "Test Oct 9",
            "description": "Assign Promotion Test"
        },
        {
            "startDate": "2013-09-27",
            "promotionItem": [],
            "accountId": null,
            "orderItemDiscount": "true",
            "discountAmount": "1.0",
            "discountPercentage": "0.0",
            "endDate": "2013-09-28",
            "title": "Test Promotion",
            "description": "1$ off Test"
        },
        {
            "startDate": null,
            "promotionItem": [],
            "accountId": null,
            "orderItemDiscount": "false",
            "discountAmount": null,
            "discountPercentage": "0.0",
            "endDate": null,
            "title": "BOGO test",
            "description": null
        }
    ]
}